LICENSE
MANIFEST.in
README.rst
requirements.txt
setup.cfg
setup.py
flaskup/__init__.py
flaskup/console.py
flaskup/errorhandler.py
flaskup/filters.py
flaskup/i18n.py
flaskup/jsonutils.py
flaskup/models.py
flaskup/utils.py
flaskup/views.py
flaskup.egg-info/PKG-INFO
flaskup.egg-info/SOURCES.txt
flaskup.egg-info/dependency_links.txt
flaskup.egg-info/entry_points.txt
flaskup.egg-info/not-zip-safe
flaskup.egg-info/requires.txt
flaskup.egg-info/top_level.txt
flaskup/static/bootstrap-modal.js
flaskup/static/jquery-1.7.2.min.js
flaskup/static/style.css
flaskup/static/uploading.gif
flaskup/static/bootstrap/css/bootstrap-responsive.css
flaskup/static/bootstrap/css/bootstrap-responsive.min.css
flaskup/static/bootstrap/css/bootstrap.css
flaskup/static/bootstrap/css/bootstrap.min.css
flaskup/static/bootstrap/img/glyphicons-halflings-white.png
flaskup/static/bootstrap/img/glyphicons-halflings.png
flaskup/static/bootstrap/js/bootstrap.js
flaskup/static/bootstrap/js/bootstrap.min.js
flaskup/templates/404.html
flaskup/templates/500.html
flaskup/templates/base.html
flaskup/templates/show_delete_file.html
flaskup/templates/show_get_file.html
flaskup/templates/show_upload_form.html
flaskup/templates/show_uploaded_file.html
flaskup/templates/emails/notify_add_body.txt
flaskup/templates/emails/notify_add_subject.txt
flaskup/templates/emails/notify_contact_body.txt
flaskup/templates/emails/notify_contact_subject.txt
flaskup/templates/emails/notify_delete_body.txt
flaskup/templates/emails/notify_delete_subject.txt
flaskup/templates/emails/notify_me_body.txt
flaskup/templates/emails/notify_me_subject.txt
flaskup/translations/babel.cfg
flaskup/translations/messages.pot
flaskup/translations/de/LC_MESSAGES/messages.mo
flaskup/translations/de/LC_MESSAGES/messages.po
flaskup/translations/fr/LC_MESSAGES/messages.mo
flaskup/translations/fr/LC_MESSAGES/messages.po