Metadata-Version: 1.1
Name: flaskup
Version: 0.3.2
Summary: A simple Flask application to share files.
Home-page: http://git.deltalima.net/flaskup/
Author: Laurent Meunier
Author-email: laurent@deltalima.net
License: BSD
Download-URL: http://git.deltalima.net/flaskup/snapshot/flaskup-0.3.2.tar.gz
Platform: UNKNOWN
Classifier: License :: OSI Approved :: BSD License
Classifier: Development Status :: 4 - Beta
Classifier: Environment :: Web Environment
Classifier: Intended Audience :: System Administrators
Classifier: License :: OSI Approved :: BSD License
Classifier: Operating System :: OS Independent
Classifier: Programming Language :: Python
Classifier: Topic :: Communications :: File Sharing
Classifier: Topic :: Internet
Classifier: Topic :: Internet :: WWW/HTTP :: WSGI :: Application
